setup.py
TracLdapPlugin.egg-info/PKG-INFO
TracLdapPlugin.egg-info/SOURCES.txt
TracLdapPlugin.egg-info/dependency_links.txt
TracLdapPlugin.egg-info/entry_points.txt
TracLdapPlugin.egg-info/requires.txt
TracLdapPlugin.egg-info/top_level.txt
trac_ldap_plugin/__init__.py
trac_ldap_plugin/api.py