Metadata-Version: 1.0
Name: TracLdapPlugin
Version: 0.7.1
Summary: LDAP extensions for Trac 0.12
Home-page: http://trac-hacks.org/wiki/LdapPlugin
Author: Stefan Richter, Emmanuel Blot
Author-email: stefan@02strich.de
License: BSD
Keywords: trac ldap permission group acl
Platform: UNKNOWN
